elephantlabs/__init__.py
elephantlabs/datamodels.py
elephantlabs/datasets.py
elephantlabs/debug.py
elephantlabs/inferencers.py
elephantlabs/models.py
elephantlabs/solvers.py
elephantlabs/utils.py
elephantlabs-20.12.1.dist-info/LICENSE
elephantlabs-20.12.1.dist-info/METADATA
elephantlabs-20.12.1.dist-info/WHEEL
elephantlabs-20.12.1.dist-info/top_level.txt
elephantlabs-20.12.1.dist-info/RECORD
