Metadata-Version: 2.1
Name: elephantlabs
Version: 20.12.1
Summary: This package contains the code necessary to use and reproduce our models and projects.
Home-page: https://www.elephantlabs.ai
Author: Jerome Wassmuth
Author-email: jerome.wassmuth@elephantlabs.ai
License: UNKNOWN
Platform: UNKNOWN
Classifier: Programming Language :: Python :: 3
Classifier: License :: OSI Approved :: MIT License
Classifier: Operating System :: OS Independent
Requires-Python: >=3.6
